pytify_stats/__main__.py
pytify_stats/_init_.py
pytify_stats/client.py
pytify_stats-0.0.10.dist-info/LICENSE
pytify_stats-0.0.10.dist-info/METADATA
pytify_stats-0.0.10.dist-info/WHEEL
pytify_stats-0.0.10.dist-info/entry_points.txt
pytify_stats-0.0.10.dist-info/top_level.txt
pytify_stats-0.0.10.dist-info/RECORD
