Metadata-Version: 2.1
Name: pytify_stats
Version: 0.0.10
Summary: A Python package that allows users to gather advanced artist statistics from Spotify
Author-email: Rak Sridhar <rss9243@nyu.edu>
License: GNU GENERAL PUBLIC LICENSE
Project-URL: Homepage, https://github.com/software-students-spring2024/3-python-package-exercise-team-7
Project-URL: Repository, https://github.com/software-students-spring2024/3-python-package-exercise-team-7.git
Keywords: python,package,build,tutorial
Classifier: Programming Language :: Python :: 3
Classifier: Intended Audience :: Education
Classifier: License :: OSI Approved :: GNU General Public License v3 (GPLv3)
Classifier: Operating System :: OS Independent
Requires-Python: >=3.7
License-File: LICENSE
Provides-Extra: dev
Requires-Dist: pytest ; extra == 'dev'
